pyscim/__init__.py
pyscim/api_client.py
pyscim/configuration.py
pyscim/exceptions.py
pyscim/model_utils.py
pyscim/rest.py
pyscim/api/__init__.py
pyscim/api/default_api.py
pyscim/api/discovery_api.py
pyscim/api/fido2_devices_api.py
pyscim/api/fido_devices_api.py
pyscim/api/global_search_api.py
pyscim/api/group_api.py
pyscim/api/user_api.py
pyscim/apis/__init__.py
pyscim/model/__init__.py
pyscim/model/address.py
pyscim/model/base_resource.py
pyscim/model/basic_list_response.py
pyscim/model/bulk_data.py
pyscim/model/bulk_operation.py
pyscim/model/bulk_request.py
pyscim/model/bulk_request_all_of.py
pyscim/model/email.py
pyscim/model/entitlement.py
pyscim/model/error_response.py
pyscim/model/fido2_device_resource.py
pyscim/model/fido2_device_resource_all_of.py
pyscim/model/fido2_list_response.py
pyscim/model/fido2_list_response_all_of.py
pyscim/model/fido_device_resource.py
pyscim/model/fido_device_resource_all_of.py
pyscim/model/fido_list_response.py
pyscim/model/fido_list_response_all_of.py
pyscim/model/generic_list_response.py
pyscim/model/generic_list_response_all_of.py
pyscim/model/generic_resource.py
pyscim/model/group.py
pyscim/model/group_list_response.py
pyscim/model/group_list_response_all_of.py
pyscim/model/group_resource.py
pyscim/model/group_resource_all_of.py
pyscim/model/instant_messaging_address.py
pyscim/model/member.py
pyscim/model/meta.py
pyscim/model/name.py
pyscim/model/patch_operation.py
pyscim/model/patch_request.py
pyscim/model/phone_number.py
pyscim/model/photo.py
pyscim/model/resource_type.py
pyscim/model/resource_type_list_response.py
pyscim/model/resource_type_list_response_all_of.py
pyscim/model/resource_type_schema_extensions.py
pyscim/model/role.py
pyscim/model/schema_attribute.py
pyscim/model/schema_list_response.py
pyscim/model/schema_list_response_all_of.py
pyscim/model/schema_resource.py
pyscim/model/search_request.py
pyscim/model/service_provider_config_response.py
pyscim-1.0.0.dist-info/METADATA
pyscim-1.0.0.dist-info/WHEEL
pyscim-1.0.0.dist-info/top_level.txt
pyscim-1.0.0.dist-info/RECORD
