Metadata-Version: 2.1
Name: pyscim
Version: 1.0.0
Summary: SCIM API
Home-page: UNKNOWN
Author: OpenAPI Generator community
Author-email: team@openapitools.org
License: Janssen License
Keywords: OpenAPI,OpenAPI-Generator,SCIM API
Platform: UNKNOWN
Requires-Python: >=3.6
Requires-Dist: urllib3 (>=1.25.3)
Requires-Dist: python-dateutil
